tropo/__init__.py
tropo/base.py
tropo/compute.py
tropo/func.py
tropo/network.py
tropo/storage.py
tropo-0.2.1.dist-info/DESCRIPTION.rst
tropo-0.2.1.dist-info/METADATA
tropo-0.2.1.dist-info/RECORD
tropo-0.2.1.dist-info/WHEEL
tropo-0.2.1.dist-info/metadata.json
tropo-0.2.1.dist-info/top_level.txt
