Metadata-Version: 2.0
Name: tropo
Version: 0.2.1
Summary: Azure Resource Template Generator
Home-page: https://github.com/hoffmann/tropo
Author: Peter Hoffmann
Author-email: ph@peter-hoffmann.com
License: BSD
Platform: UNKNOWN
Classifier: Programming Language :: Python
